[
    {
        "id": "529b1c45-6162-473c-a180-c202a20b4fd3",
        "title": "Kittie",
        "url": "/src/assets/kitty.jpg"
    },
    {
        "id": "87327c31-e80a-4724-be44-8e65ae9a1dff",
        "title": "Kitten",
        "url": "/src/assets/kitten.jpg"
    },
    {
        "id": "1967416f-0a1a-48d8-8757-30857ba0d2dc",
        "title": "furball",
        "url": "/src/assets/furball.jpg"
    },
    {
        "id": "098d9a46-8497-4ee4-b4ad-5d3cd506dd4f",
        "title": "whiskers",
        "url": "/src/assets/whiskers.jpg"
    },
    {
        "id": "0ea1fd1a-1483-4f25-9b87-947695fbd6dd",
        "title": "tabby",
        "url": "/src/assets/tabby.jpg"
    },
    {
        "id": "0ece32d5-4c0e-481c-8a0c-93f05e5c2934",
        "title": "puss",
        "url": "/src/assets/puss.jpg"
    },
    {
        "id": "257ed8c4-f780-47ef-b499-d645b95b8b9c",
        "title": "moggie",
        "url": "/src/assets/moggie.jpg"
    },
    {
        "id": "f5b3b1f1-6b6b-4b7f-8f1d-6f2b5f4f3f3b",
        "title": "aniutica",
        "url": "/src/assets/aniutica.jpeg"
    }
]
